{
    "lyrics": [
        {
            "time": 875,
            "text": "君が少し俯いたまま",
            "furigana": {
                "positions": [
                    0,
                    2,
                    4
                ],
                "kanji": [
                    "君",
                    "少",
                    "俯"
                ],
                "readings": [
                    "きみ",
                    "すこ",
                    "うつむ"
                ]
            }
        },
        {
            "time": 3827,
            "text": "話していたからさ",
            "furigana": {
                "positions": [
                    0
                ],
                "kanji": [
                    "話"
                ],
                "readings": [
                    "はな"
                ]
            }
        },
        {
            "time": 7536,
            "text": "いつもより一歩近く歩いてみたんだ",
            "furigana": {
                "positions": [
                    5,
                    7,
                    9
                ],
                "kanji": [
                    "一歩",
                    "近",
                    "歩"
                ],
                "readings": [
                    "いっぽ",
                    "ちか",
                    "ある"
                ]
            }
        },
        {
            "time": 19526,
            "text": "夕陽　時計の針のように",
            "furigana": {
                "positions": [
                    0,
                    3,
                    6
                ],
                "kanji": [
                    "夕陽",
                    "時計",
                    "針"
                ],
                "readings": [
                    "ゆうひ",
                    "とけい",
                    "はり"
                ]
            }
        },
        {
            "time": 22426,
            "text": "影が背伸びしていく",
            "furigana": {
                "positions": [
                    0,
                    2
                ],
                "kanji": [
                    "影",
                    "背伸"
                ],
                "readings": [
                    "かげ",
                    "せの"
                ]
            }
        },
        {
            "time": 26031,
            "text": "街は急ぎ足　次の季節の声がした",
            "furigana": {
                "positions": [
                    0,
                    2,
                    4,
                    6,
                    8,
                    11
                ],
                "kanji": [
                    "街",
                    "急",
                    "足",
                    "次",
                    "季節",
                    "声"
                ],
                "readings": [
                    "まち",
                    "いそ",
                    "あし",
                    "つぎ",
                    "きせつ",
                    "こえ"
                ]
            }
        },
        {
            "time": 33188,
            "text": "愛とか言うのも",
            "furigana": {
                "positions": [
                    0,
                    3
                ],
                "kanji": [
                    "愛",
                    "言"
                ],
                "readings": [
                    "あい",
                    "い"
                ]
            }
        },
        {
            "time": 34991,
            "text": "言葉にしちゃ呆気ないもんだな",
            "furigana": {
                "positions": [
                    0,
                    6
                ],
                "kanji": [
                    "言葉",
                    "呆気"
                ],
                "readings": [
                    "ことば",
                    "あっけ"
                ]
            }
        },
        {
            "time": 39876,
            "text": "1人にさえならなきゃ",
            "furigana": {
                "positions": [
                    0
                ],
                "kanji": [
                    "1人"
                ],
                "readings": [
                    "ひとり"
                ]
            }
        },
        {
            "time": 41861,
            "text": "理解出来るもんだと思ってた",
            "furigana": {
                "positions": [
                    0,
                    2,
                    9
                ],
                "kanji": [
                    "理解",
                    "出来",
                    "思"
                ],
                "readings": [
                    "りかい",
                    "でき",
                    "おも"
                ]
            }
        },
        {
            "time": 47060,
            "text": "あの街灯はこれまで",
            "furigana": {
                "positions": [
                    2
                ],
                "kanji": [
                    "街灯"
                ],
                "readings": [
                    "がいとう"
                ]
            }
        },
        {
            "time": 50795,
            "text": "誰を導いてきたの",
            "furigana": {
                "positions": [
                    0,
                    2
                ],
                "kanji": [
                    "誰",
                    "導"
                ],
                "readings": [
                    "だれ",
                    "みちび"
                ]
            }
        },
        {
            "time": 54217,
            "text": "見てごらん、綺麗だよ",
            "furigana": {
                "positions": [
                    0,
                    6
                ],
                "kanji": [
                    "見",
                    "綺麗"
                ],
                "readings": [
                    "み",
                    "きれい"
                ]
            }
        },
        {
            "time": 58997,
            "text": "約束の言葉",
            "furigana": {
                "positions": [
                    0,
                    3
                ],
                "kanji": [
                    "約束",
                    "言葉"
                ],
                "readings": [
                    "やくそく",
                    "ことば"
                ]
            }
        },
        {
            "time": 61584,
            "text": "大好きな花",
            "furigana": {
                "positions": [
                    0,
                    4
                ],
                "kanji": [
                    "大好",
                    "花"
                ],
                "readings": [
                    "だいす",
                    "はな"
                ]
            }
        },
        {
            "time": 63412,
            "text": "ポッケの宝物",
            "furigana": {
                "positions": [
                    4
                ],
                "kanji": [
                    "宝物"
                ],
                "readings": [
                    "たからもの"
                ]
            }
        },
        {
            "time": 66886,
            "text": "そんなキラキラごと君も",
            "furigana": {
                "positions": [
                    9
                ],
                "kanji": [
                    "君"
                ],
                "readings": [
                    "きみ"
                ]
            }
        },
        {
            "time": 70152,
            "text": "消えちゃいそうでさ",
            "furigana": {
                "positions": [
                    0
                ],
                "kanji": [
                    "消"
                ],
                "readings": [
                    "き"
                ]
            }
        },
        {
            "time": 72921,
            "text": "走り出していた",
            "furigana": {
                "positions": [
                    0,
                    2
                ],
                "kanji": [
                    "走",
                    "出"
                ],
                "readings": [
                    "はし",
                    "だ"
                ]
            }
        },
        {
            "time": 75089,
            "text": "間に合うかな？",
            "furigana": {
                "positions": [
                    0,
                    2
                ],
                "kanji": [
                    "間",
                    "合"
                ],
                "readings": [
                    "ま",
                    "あ"
                ]
            }
        },
        {
            "time": 77100,
            "text": "手は握ってるよ",
            "furigana": {
                "positions": [
                    0,
                    2
                ],
                "kanji": [
                    "手",
                    "握"
                ],
                "readings": [
                    "て",
                    "にぎ"
                ]
            }
        },
        {
            "time": 79530,
            "text": "多分この世界広くはない",
            "furigana": {
                "positions": [
                    0,
                    4,
                    6
                ],
                "kanji": [
                    "多分",
                    "世界",
                    "広"
                ],
                "readings": [
                    "たぶん",
                    "せかい",
                    "ひろ"
                ]
            }
        },
        {
            "time": 83683,
            "text": "今日は僕が一歩踏み出すから",
            "furigana": {
                "positions": [
                    0,
                    3,
                    5,
                    7,
                    9
                ],
                "kanji": [
                    "今日",
                    "僕",
                    "一歩",
                    "踏",
                    "出"
                ],
                "readings": [
                    "きょう",
                    "ぼく",
                    "いっぽ",
                    "ふ",
                    "だ"
                ]
            }
        },
        {
            "time": 90527,
            "text": "夜更け時計の針以外",
            "furigana": {
                "positions": [
                    0,
                    3,
                    6,
                    7
                ],
                "kanji": [
                    "夜更",
                    "時計",
                    "針",
                    "以外"
                ],
                "readings": [
                    "よふ",
                    "とけい",
                    "はり",
                    "いがい"
                ]
            }
        },
        {
            "time": 93296,
            "text": "音を失った部屋",
            "furigana": {
                "positions": [
                    0,
                    2,
                    5
                ],
                "kanji": [
                    "音",
                    "失",
                    "部屋"
                ],
                "readings": [
                    "おと",
                    "うしな",
                    "へや"
                ]
            }
        },
        {
            "time": 96901,
            "text": "大切なものは夢に連れていったりもした",
            "furigana": {
                "positions": [
                    0,
                    6,
                    8
                ],
                "kanji": [
                    "大切",
                    "夢",
                    "連"
                ],
                "readings": [
                    "たいせつ",
                    "ゆめ",
                    "つ"
                ]
            }
        },
        {
            "time": 104189,
            "text": "そんな事をさ",
            "furigana": {
                "positions": [
                    3
                ],
                "kanji": [
                    "事"
                ],
                "readings": [
                    "こと"
                ]
            }
        },
        {
            "time": 105626,
            "text": "いつまでも覚えてるままで",
            "furigana": {
                "positions": [
                    5
                ],
                "kanji": [
                    "覚"
                ],
                "readings": [
                    "おぼ"
                ]
            }
        },
        {
            "time": 110877,
            "text": "瞬きの間に",
            "furigana": {
                "positions": [
                    0,
                    3
                ],
                "kanji": [
                    "瞬",
                    "間"
                ],
                "readings": [
                    "まばた",
                    "あいだ"
                ]
            }
        },
        {
            "time": 112548,
            "text": "見逃したものばかり信じた",
            "furigana": {
                "positions": [
                    0,
                    9
                ],
                "kanji": [
                    "見逃",
                    "信"
                ],
                "readings": [
                    "みのが",
                    "しん"
                ]
            }
        },
        {
            "time": 117068,
            "text": "行かなくちゃ信号の青と赤",
            "furigana": {
                "positions": [
                    0,
                    6,
                    9,
                    11
                ],
                "kanji": [
                    "行",
                    "信号",
                    "青",
                    "赤"
                ],
                "readings": [
                    "い",
                    "しんごう",
                    "あお",
                    "あか"
                ]
            }
        },
        {
            "time": 121744,
            "text": "僕の探してる何だか",
            "furigana": {
                "positions": [
                    0,
                    2,
                    6
                ],
                "kanji": [
                    "僕",
                    "探",
                    "何"
                ],
                "readings": [
                    "ぼく",
                    "さが",
                    "なん"
                ]
            }
        },
        {
            "time": 125166,
            "text": "何かに似ているよ",
            "furigana": {
                "positions": [
                    0,
                    3
                ],
                "kanji": [
                    "何",
                    "似"
                ],
                "readings": [
                    "なに",
                    "に"
                ]
            }
        },
        {
            "time": 130129,
            "text": "君は指差した",
            "furigana": {
                "positions": [
                    0,
                    2,
                    3
                ],
                "kanji": [
                    "君",
                    "指",
                    "差"
                ],
                "readings": [
                    "きみ",
                    "ゆび",
                    "さ"
                ]
            }
        },
        {
            "time": 132637,
            "text": "空の色と　その変わり方を",
            "furigana": {
                "positions": [
                    0,
                    2,
                    7,
                    10
                ],
                "kanji": [
                    "空",
                    "色",
                    "変",
                    "方"
                ],
                "readings": [
                    "そら",
                    "いろ",
                    "か",
                    "かた"
                ]
            }
        },
        {
            "time": 137835,
            "text": "立て続くふりと綺麗に",
            "furigana": {
                "positions": [
                    0,
                    2,
                    7
                ],
                "kanji": [
                    "立",
                    "続",
                    "綺麗"
                ],
                "readings": [
                    "た",
                    "つづ",
                    "きれい"
                ]
            }
        },
        {
            "time": 141205,
            "text": "変わってくもんだな",
            "furigana": {
                "positions": [
                    0
                ],
                "kanji": [
                    "変"
                ],
                "readings": [
                    "か"
                ]
            }
        },
        {
            "time": 143922,
            "text": "分かり始めてた",
            "furigana": {
                "positions": [
                    0,
                    3
                ],
                "kanji": [
                    "分",
                    "始"
                ],
                "readings": [
                    "わ",
                    "はじ"
                ]
            }
        },
        {
            "time": 146299,
            "text": "大切な物",
            "furigana": {
                "positions": [
                    0,
                    3
                ],
                "kanji": [
                    "大切",
                    "物"
                ],
                "readings": [
                    "たいせつ",
                    "もの"
                ]
            }
        },
        {
            "time": 147944,
            "text": "それは躍る事",
            "furigana": {
                "positions": [
                    3,
                    5
                ],
                "kanji": [
                    "躍",
                    "事"
                ],
                "readings": [
                    "おど",
                    "こと"
                ]
            }
        },
        {
            "time": 150713,
            "text": "だから残らずここには無い",
            "furigana": {
                "positions": [
                    3,
                    10
                ],
                "kanji": [
                    "残",
                    "無"
                ],
                "readings": [
                    "のこ",
                    "な"
                ]
            }
        },
        {
            "time": 154710,
            "text": "嫌になるくらい思い出せるのに",
            "furigana": {
                "positions": [
                    0,
                    7,
                    9
                ],
                "kanji": [
                    "嫌",
                    "思",
                    "出"
                ],
                "readings": [
                    "いや",
                    "おも",
                    "だ"
                ]
            }
        },
        {
            "time": 191673,
            "text": "空の色の変わり方を",
            "furigana": {
                "positions": [
                    0,
                    2,
                    4,
                    7
                ],
                "kanji": [
                    "空",
                    "色",
                    "変",
                    "方"
                ],
                "readings": [
                    "そら",
                    "いろ",
                    "か",
                    "かた"
                ]
            }
        },
        {
            "time": 194860,
            "text": "初めて見たあの日",
            "furigana": {
                "positions": [
                    0,
                    3,
                    7
                ],
                "kanji": [
                    "初",
                    "見",
                    "日"
                ],
                "readings": [
                    "はじ",
                    "み",
                    "ひ"
                ]
            }
        },
        {
            "time": 198465,
            "text": "君と同じ景色を見て",
            "furigana": {
                "positions": [
                    0,
                    2,
                    4,
                    7
                ],
                "kanji": [
                    "君",
                    "同",
                    "景色",
                    "見"
                ],
                "readings": [
                    "きみ",
                    "おな",
                    "けしき",
                    "み"
                ]
            }
        },
        {
            "time": 201704,
            "text": "僕が泣いてたあの日",
            "furigana": {
                "positions": [
                    0,
                    2,
                    8
                ],
                "kanji": [
                    "僕",
                    "泣",
                    "日"
                ],
                "readings": [
                    "ぼく",
                    "な",
                    "ひ"
                ]
            }
        },
        {
            "time": 206197,
            "text": "約束しようか",
            "furigana": {
                "positions": [
                    0
                ],
                "kanji": [
                    "約束"
                ],
                "readings": [
                    "やくそく"
                ]
            }
        },
        {
            "time": 208705,
            "text": "きっと僕らは",
            "furigana": {
                "positions": [
                    3
                ],
                "kanji": [
                    "僕"
                ],
                "readings": [
                    "ぼく"
                ]
            }
        },
        {
            "time": 210403,
            "text": "出会えてよかった",
            "furigana": {
                "positions": [
                    0
                ],
                "kanji": [
                    "出会"
                ],
                "readings": [
                    "であ"
                ]
            }
        },
        {
            "time": 213930,
            "text": "愛だとかなんとかって奴に",
            "furigana": {
                "positions": [
                    0,
                    10
                ],
                "kanji": [
                    "愛",
                    "奴"
                ],
                "readings": [
                    "あい",
                    "やつ"
                ]
            }
        },
        {
            "time": 217195,
            "text": "頼ってみたいのさ",
            "furigana": {
                "positions": [
                    0
                ],
                "kanji": [
                    "頼"
                ],
                "readings": [
                    "たよ"
                ]
            }
        },
        {
            "time": 220068,
            "text": "走り出していた",
            "furigana": {
                "positions": [
                    0,
                    2
                ],
                "kanji": [
                    "走",
                    "出"
                ],
                "readings": [
                    "はし",
                    "だ"
                ]
            }
        },
        {
            "time": 222184,
            "text": "間に合うかな",
            "furigana": {
                "positions": [
                    0,
                    2
                ],
                "kanji": [
                    "間",
                    "合"
                ],
                "readings": [
                    "ま",
                    "あ"
                ]
            }
        },
        {
            "time": 224091,
            "text": "手は握ってるよ",
            "furigana": {
                "positions": [
                    0,
                    2
                ],
                "kanji": [
                    "手",
                    "握"
                ],
                "readings": [
                    "て",
                    "にぎ"
                ]
            }
        },
        {
            "time": 226495,
            "text": "今は願う未来君と見たい",
            "furigana": {
                "positions": [
                    0,
                    2,
                    4,
                    6,
                    8
                ],
                "kanji": [
                    "今",
                    "願",
                    "未来",
                    "君",
                    "見"
                ],
                "readings": [
                    "いま",
                    "ねが",
                    "みらい",
                    "きみ",
                    "み"
                ]
            }
        },
        {
            "time": 230674,
            "text": "そう気づいてからは早かった",
            "furigana": {
                "positions": [
                    2,
                    9
                ],
                "kanji": [
                    "気",
                    "早"
                ],
                "readings": [
                    "き",
                    "はや"
                ]
            }
        },
        {
            "time": 234540,
            "text": "南南西に強い光",
            "furigana": {
                "positions": [
                    0,
                    4,
                    6
                ],
                "kanji": [
                    "南南西",
                    "強",
                    "光"
                ],
                "readings": [
                    "なんなんせい",
                    "つよ",
                    "ひかり"
                ]
            }
        },
        {
            "time": 237283,
            "text": "ずっと追い続けた",
            "furigana": {
                "positions": [
                    3,
                    5
                ],
                "kanji": [
                    "追",
                    "続"
                ],
                "readings": [
                    "お",
                    "つづ"
                ]
            }
        },
        {
            "time": 241123,
            "text": "明日明後日も",
            "furigana": {
                "positions": [
                    0,
                    2
                ],
                "kanji": [
                    "明日",
                    "明後日"
                ],
                "readings": [
                    "あす",
                    "あさって"
                ]
            }
        },
        {
            "time": 242952,
            "text": "その先でも変わる空の下で",
            "furigana": {
                "positions": [
                    2,
                    5,
                    8,
                    10
                ],
                "kanji": [
                    "先",
                    "変",
                    "空",
                    "下"
                ],
                "readings": [
                    "さき",
                    "か",
                    "そら",
                    "した"
                ]
            }
        },
        {
            "time": 247811,
            "text": "段々顔を上げる2人離さないでいた",
            "furigana": {
                "positions": [
                    0,
                    2,
                    4,
                    7,
                    9
                ],
                "kanji": [
                    "段",
                    "顔",
                    "上",
                    "2人",
                    "離"
                ],
                "readings": [
                    "だん",
                    "かお",
                    "あ",
                    "ふたり",
                    "はな"
                ]
            }
        },
        {
            "time": 253531,
            "text": "多分この世界広くはない",
            "furigana": {
                "positions": [
                    0,
                    4,
                    6
                ],
                "kanji": [
                    "多分",
                    "世界",
                    "広"
                ],
                "readings": [
                    "たぶん",
                    "せかい",
                    "ひろ"
                ]
            }
        },
        {
            "time": 257920,
            "text": "絶えず僕は1歩踏み出すから",
            "furigana": {
                "positions": [
                    0,
                    3,
                    5,
                    7,
                    9
                ],
                "kanji": [
                    "絶",
                    "僕",
                    "1歩",
                    "踏",
                    "出"
                ],
                "readings": [
                    "た",
                    "ぼく",
                    "いっぽ",
                    "ふ",
                    "だ"
                ]
            }
        },
        {
            "time": 262962,
            "text": "とても眩しかった",
            "furigana": {
                "positions": [
                    3
                ],
                "kanji": [
                    "眩"
                ],
                "readings": [
                    "まぶ"
                ]
            }
        },
        {
            "time": 266279,
            "text": "君は笑っていた",
            "furigana": {
                "positions": [
                    0,
                    2
                ],
                "kanji": [
                    "君",
                    "笑"
                ],
                "readings": [
                    "きみ",
                    "わら"
                ]
            }
        }
    ]
}